{
  "packageName": "java.rmi.activation",
  "simpleName": "ActivationDesc",
  "moduleName": "java.rmi",
  "type": "CLASS",
  "superClass": {
    "name": "java.lang.Object",
    "type": "Class"
  },
  "members": [
    {
      "returnType": {
        "name": "java.rmi.activation.ActivationGroupID",
        "type": "Class"
      },
      "parameters": [],
      "isDefaultMethod": false,
      "memberType": "JavaMethod",
      "modifiers": 1,
      "name": "getGroupID",
      "comment": "Returns the group identifier for the object specified by this descriptor. A group provides a way to aggregate objects into a single Java virtual machine. RMI creates/activates objects with the same groupID in the same virtual machine.",
      "annotations": [],
      "tagMap": {
        "return": [
          "the group identifier"
        ],
        "since": [
          "1.2"
        ]
      }
    },
    {
      "returnType": {
        "name": "java.lang.String",
        "type": "Class"
      },
      "parameters": [],
      "isDefaultMethod": false,
      "memberType": "JavaMethod",
      "modifiers": 1,
      "name": "getClassName",
      "comment": "Returns the class name for the object specified by this descriptor.",
      "annotations": [],
      "tagMap": {
        "return": [
          "the class name"
        ],
        "since": [
          "1.2"
        ]
      }
    },
    {
      "returnType": {
        "name": "java.lang.String",
        "type": "Class"
      },
      "parameters": [],
      "isDefaultMethod": false,
      "memberType": "JavaMethod",
      "modifiers": 1,
      "name": "getLocation",
      "comment": "Returns the code location for the object specified by this descriptor.",
      "annotations": [],
      "tagMap": {
        "return": [
          "the code location"
        ],
        "since": [
          "1.2"
        ]
      }
    },
    {
      "returnType": {
        "name": "java.rmi.MarshalledObject",
        "parameters": [
          {
            "type": "Wildcard"
          }
        ],
        "type": "Class"
      },
      "parameters": [],
      "isDefaultMethod": false,
      "memberType": "JavaMethod",
      "modifiers": 1,
      "name": "getData",
      "comment": "Returns a \"marshalled object\" containing intialization/activation data for the object specified by this descriptor.",
      "annotations": [],
      "tagMap": {
        "return": [
          "the object specific \"initialization\" data"
        ],
        "since": [
          "1.2"
        ]
      }
    },
    {
      "returnType": {
        "name": "boolean",
        "type": "Class"
      },
      "parameters": [],
      "isDefaultMethod": false,
      "memberType": "JavaMethod",
      "modifiers": 1,
      "name": "getRestartMode",
      "comment": "Returns the \"restart\" mode of the object associated with this activation descriptor.",
      "annotations": [],
      "tagMap": {
        "return": [
          "true if the activatable object associated with this activation descriptor is restarted via the activation daemon when either the daemon comes up or the object\u0027s group is restarted after an unexpected crash; otherwise it returns false, meaning that the object is only activated on demand via a method call. Note that if the restart mode is \n\u003ccode\u003etrue\u003c/code\u003e, the activator does not force an initial immediate activation of a newly registered object; initial activation is lazy."
        ],
        "since": [
          "1.2"
        ]
      }
    },
    {
      "returnType": {
        "name": "boolean",
        "type": "Class"
      },
      "parameters": [
        {
          "annotations": [],
          "type": {
            "name": "java.lang.Object",
            "type": "Class"
          },
          "name": "obj",
          "varargs": false
        }
      ],
      "isDefaultMethod": false,
      "memberType": "JavaMethod",
      "modifiers": 1,
      "name": "equals",
      "comment": "Compares two activation descriptors for content equality.",
      "annotations": [],
      "tagMap": {
        "see": [
          "\u003ca href\u003d\"https://docs.oracle.com/en/java/javase/16/docs/api/java.base/java/util/Hashtable.html\" title\u003d\"class in java.util\"\u003e\u003ccode\u003eHashtable\u003c/code\u003e\u003c/a\u003e"
        ],
        "Overrides:": [
          "\u003ccode\u003e\u003ca href\u003d\"https://docs.oracle.com/en/java/javase/16/docs/api/java.base/java/lang/Object.html#equals(java.lang.Object)\"\u003eequals\u003c/a\u003e\u003c/code\u003e\u0026nbsp;in class\u0026nbsp;\n\u003ccode\u003e\u003ca href\u003d\"https://docs.oracle.com/en/java/javase/16/docs/api/java.base/java/lang/Object.html\" title\u003d\"class in java.lang\"\u003eObject\u003c/a\u003e\u003c/code\u003e"
        ],
        "param": [
          "\u003ccode\u003eobj\u003c/code\u003e - the Object to compare with"
        ],
        "return": [
          "true if these Objects are equal; false otherwise."
        ],
        "since": [
          "1.2"
        ]
      }
    },
    {
      "returnType": {
        "name": "int",
        "type": "Class"
      },
      "parameters": [],
      "isDefaultMethod": false,
      "memberType": "JavaMethod",
      "modifiers": 1,
      "name": "hashCode",
      "comment": "Return the same hashCode for similar ActivationDescs.",
      "annotations": [],
      "tagMap": {
        "see": [
          "\u003ca href\u003d\"https://docs.oracle.com/en/java/javase/16/docs/api/java.base/java/util/Hashtable.html\" title\u003d\"class in java.util\"\u003e\u003ccode\u003eHashtable\u003c/code\u003e\u003c/a\u003e"
        ],
        "Overrides:": [
          "\u003ccode\u003e\u003ca href\u003d\"https://docs.oracle.com/en/java/javase/16/docs/api/java.base/java/lang/Object.html#hashCode()\"\u003ehashCode\u003c/a\u003e\u003c/code\u003e\u0026nbsp;in class\u0026nbsp;\n\u003ccode\u003e\u003ca href\u003d\"https://docs.oracle.com/en/java/javase/16/docs/api/java.base/java/lang/Object.html\" title\u003d\"class in java.lang\"\u003eObject\u003c/a\u003e\u003c/code\u003e"
        ],
        "return": [
          "an integer"
        ]
      }
    },
    {
      "throwsClasses": [
        {
          "name": "java.rmi.activation.ActivationException",
          "type": "Class"
        }
      ],
      "parameters": [
        {
          "annotations": [],
          "type": {
            "name": "java.lang.String",
            "type": "Class"
          },
          "name": "className",
          "varargs": false
        },
        {
          "annotations": [],
          "type": {
            "name": "java.lang.String",
            "type": "Class"
          },
          "name": "location",
          "varargs": false
        },
        {
          "annotations": [],
          "type": {
            "name": "java.rmi.MarshalledObject",
            "parameters": [
              {
                "type": "Wildcard"
              }
            ],
            "type": "Class"
          },
          "name": "data",
          "varargs": false
        }
      ],
      "isDefaultMethod": false,
      "memberType": "JavaMethod",
      "modifiers": 1,
      "comment": "Constructs an object descriptor for an object whose class name is className, that can be loaded from the code location and whose initialization information is data. If this form of the constructor is used, the groupID defaults to the current id for ActivationGroup for this VM. All objects with the same ActivationGroupID are activated in the same VM. Note that objects specified by a descriptor created with this constructor will only be activated on demand (by default, the restart mode is false). If an activatable object requires restart services, use one of the ActivationDesc constructors that takes a boolean parameter, restart. This constructor will throw ActivationException if there is no current activation group for this VM. To create an ActivationGroup use the ActivationGroup.createGroup method.",
      "annotations": [],
      "tagMap": {
        "param": [
          "\u003ccode\u003eclassName\u003c/code\u003e - the object\u0027s fully package qualified class name",
          "\u003ccode\u003elocation\u003c/code\u003e - the object\u0027s code location (from where the class is loaded)",
          "\u003ccode\u003edata\u003c/code\u003e - the object\u0027s initialization (activation) data contained in marshalled form."
        ],
        "throws": [
          "\u003ccode\u003e\u003ca href\u003d\"https://docs.oracle.com/en/java/javase/16/docs/api/java.rmi/java/rmi/activation/ActivationException.html\" title\u003d\"class in java.rmi.activation\"\u003eActivationException\u003c/a\u003e\u003c/code\u003e - if the current group is nonexistent",
          "\u003ccode\u003e\u003ca href\u003d\"https://docs.oracle.com/en/java/javase/16/docs/api/java.base/java/lang/UnsupportedOperationException.html\" title\u003d\"class in java.lang\"\u003eUnsupportedOperationException\u003c/a\u003e\u003c/code\u003e - if and only if activation is not supported by this implementation"
        ],
        "since": [
          "1.2"
        ]
      }
    },
    {
      "throwsClasses": [
        {
          "name": "java.rmi.activation.ActivationException",
          "type": "Class"
        }
      ],
      "parameters": [
        {
          "annotations": [],
          "type": {
            "name": "java.lang.String",
            "type": "Class"
          },
          "name": "className",
          "varargs": false
        },
        {
          "annotations": [],
          "type": {
            "name": "java.lang.String",
            "type": "Class"
          },
          "name": "location",
          "varargs": false
        },
        {
          "annotations": [],
          "type": {
            "name": "java.rmi.MarshalledObject",
            "parameters": [
              {
                "type": "Wildcard"
              }
            ],
            "type": "Class"
          },
          "name": "data",
          "varargs": false
        },
        {
          "annotations": [],
          "type": {
            "name": "boolean",
            "type": "Class"
          },
          "name": "restart",
          "varargs": false
        }
      ],
      "isDefaultMethod": false,
      "memberType": "JavaMethod",
      "modifiers": 1,
      "comment": "Constructs an object descriptor for an object whose class name is className, that can be loaded from the code location and whose initialization information is data. If this form of the constructor is used, the groupID defaults to the current id for ActivationGroup for this VM. All objects with the same ActivationGroupID are activated in the same VM. This constructor will throw ActivationException if there is no current activation group for this VM. To create an ActivationGroup use the ActivationGroup.createGroup method.",
      "annotations": [],
      "tagMap": {
        "param": [
          "\u003ccode\u003eclassName\u003c/code\u003e - the object\u0027s fully package qualified class name",
          "\u003ccode\u003elocation\u003c/code\u003e - the object\u0027s code location (from where the class is loaded)",
          "\u003ccode\u003edata\u003c/code\u003e - the object\u0027s initialization (activation) data contained in marshalled form.",
          "\u003ccode\u003erestart\u003c/code\u003e - if true, the object is restarted (reactivated) when either the activator is restarted or the object\u0027s activation group is restarted after an unexpected crash; if false, the object is only activated on demand. Specifying \n\u003ccode\u003erestart\u003c/code\u003e to be \n\u003ccode\u003etrue\u003c/code\u003e does not force an initial immediate activation of a newly registered object; initial activation is lazy."
        ],
        "throws": [
          "\u003ccode\u003e\u003ca href\u003d\"https://docs.oracle.com/en/java/javase/16/docs/api/java.rmi/java/rmi/activation/ActivationException.html\" title\u003d\"class in java.rmi.activation\"\u003eActivationException\u003c/a\u003e\u003c/code\u003e - if the current group is nonexistent",
          "\u003ccode\u003e\u003ca href\u003d\"https://docs.oracle.com/en/java/javase/16/docs/api/java.base/java/lang/UnsupportedOperationException.html\" title\u003d\"class in java.lang\"\u003eUnsupportedOperationException\u003c/a\u003e\u003c/code\u003e - if and only if activation is not supported by this implementation"
        ],
        "since": [
          "1.2"
        ]
      }
    },
    {
      "parameters": [
        {
          "annotations": [],
          "type": {
            "name": "java.rmi.activation.ActivationGroupID",
            "type": "Class"
          },
          "name": "groupID",
          "varargs": false
        },
        {
          "annotations": [],
          "type": {
            "name": "java.lang.String",
            "type": "Class"
          },
          "name": "className",
          "varargs": false
        },
        {
          "annotations": [],
          "type": {
            "name": "java.lang.String",
            "type": "Class"
          },
          "name": "location",
          "varargs": false
        },
        {
          "annotations": [],
          "type": {
            "name": "java.rmi.MarshalledObject",
            "parameters": [
              {
                "type": "Wildcard"
              }
            ],
            "type": "Class"
          },
          "name": "data",
          "varargs": false
        }
      ],
      "isDefaultMethod": false,
      "memberType": "JavaMethod",
      "modifiers": 1,
      "comment": "Constructs an object descriptor for an object whose class name is className that can be loaded from the code location and whose initialization information is data. All objects with the same groupID are activated in the same Java VM. Note that objects specified by a descriptor created with this constructor will only be activated on demand (by default, the restart mode is false). If an activatable object requires restart services, use one of the ActivationDesc constructors that takes a boolean parameter, restart.",
      "annotations": [],
      "tagMap": {
        "param": [
          "\u003ccode\u003egroupID\u003c/code\u003e - the group\u0027s identifier (obtained from registering \n\u003ccode\u003eActivationSystem.registerGroup\u003c/code\u003e method). The group indicates the VM in which the object should be activated.",
          "\u003ccode\u003eclassName\u003c/code\u003e - the object\u0027s fully package-qualified class name",
          "\u003ccode\u003elocation\u003c/code\u003e - the object\u0027s code location (from where the class is loaded)",
          "\u003ccode\u003edata\u003c/code\u003e - the object\u0027s initialization (activation) data contained in marshalled form."
        ],
        "throws": [
          "\u003ccode\u003e\u003ca href\u003d\"https://docs.oracle.com/en/java/javase/16/docs/api/java.base/java/lang/IllegalArgumentException.html\" title\u003d\"class in java.lang\"\u003eIllegalArgumentException\u003c/a\u003e\u003c/code\u003e - if \n\u003ccode\u003egroupID\u003c/code\u003e is null",
          "\u003ccode\u003e\u003ca href\u003d\"https://docs.oracle.com/en/java/javase/16/docs/api/java.base/java/lang/UnsupportedOperationException.html\" title\u003d\"class in java.lang\"\u003eUnsupportedOperationException\u003c/a\u003e\u003c/code\u003e - if and only if activation is not supported by this implementation"
        ],
        "since": [
          "1.2"
        ]
      }
    },
    {
      "parameters": [
        {
          "annotations": [],
          "type": {
            "name": "java.rmi.activation.ActivationGroupID",
            "type": "Class"
          },
          "name": "groupID",
          "varargs": false
        },
        {
          "annotations": [],
          "type": {
            "name": "java.lang.String",
            "type": "Class"
          },
          "name": "className",
          "varargs": false
        },
        {
          "annotations": [],
          "type": {
            "name": "java.lang.String",
            "type": "Class"
          },
          "name": "location",
          "varargs": false
        },
        {
          "annotations": [],
          "type": {
            "name": "java.rmi.MarshalledObject",
            "parameters": [
              {
                "type": "Wildcard"
              }
            ],
            "type": "Class"
          },
          "name": "data",
          "varargs": false
        },
        {
          "annotations": [],
          "type": {
            "name": "boolean",
            "type": "Class"
          },
          "name": "restart",
          "varargs": false
        }
      ],
      "isDefaultMethod": false,
      "memberType": "JavaMethod",
      "modifiers": 1,
      "comment": "Constructs an object descriptor for an object whose class name is className that can be loaded from the code location and whose initialization information is data. All objects with the same groupID are activated in the same Java VM.",
      "annotations": [],
      "tagMap": {
        "param": [
          "\u003ccode\u003egroupID\u003c/code\u003e - the group\u0027s identifier (obtained from registering \n\u003ccode\u003eActivationSystem.registerGroup\u003c/code\u003e method). The group indicates the VM in which the object should be activated.",
          "\u003ccode\u003eclassName\u003c/code\u003e - the object\u0027s fully package-qualified class name",
          "\u003ccode\u003elocation\u003c/code\u003e - the object\u0027s code location (from where the class is loaded)",
          "\u003ccode\u003edata\u003c/code\u003e - the object\u0027s initialization (activation) data contained in marshalled form.",
          "\u003ccode\u003erestart\u003c/code\u003e - if true, the object is restarted (reactivated) when either the activator is restarted or the object\u0027s activation group is restarted after an unexpected crash; if false, the object is only activated on demand. Specifying \n\u003ccode\u003erestart\u003c/code\u003e to be \n\u003ccode\u003etrue\u003c/code\u003e does not force an initial immediate activation of a newly registered object; initial activation is lazy."
        ],
        "throws": [
          "\u003ccode\u003e\u003ca href\u003d\"https://docs.oracle.com/en/java/javase/16/docs/api/java.base/java/lang/IllegalArgumentException.html\" title\u003d\"class in java.lang\"\u003eIllegalArgumentException\u003c/a\u003e\u003c/code\u003e - if \n\u003ccode\u003egroupID\u003c/code\u003e is null",
          "\u003ccode\u003e\u003ca href\u003d\"https://docs.oracle.com/en/java/javase/16/docs/api/java.base/java/lang/UnsupportedOperationException.html\" title\u003d\"class in java.lang\"\u003eUnsupportedOperationException\u003c/a\u003e\u003c/code\u003e - if and only if activation is not supported by this implementation"
        ],
        "since": [
          "1.2"
        ]
      }
    }
  ],
  "memberType": "JavaClass",
  "modifiers": 17,
  "name": "java.rmi.activation.ActivationDesc",
  "annotations": [
    {
      "type": {
        "name": "Deprecated",
        "type": "Class"
      },
      "values": [
        {
          "name": "orRemoval",
          "value": true
        },
        {
          "name": "since",
          "value": "15"
        }
      ]
    }
  ],
  "tagMap": {
    "see": [
      "\u003ca href\u003d\"https://docs.oracle.com/en/java/javase/16/docs/api/java.rmi/java/rmi/activation/Activatable.html\" title\u003d\"class in java.rmi.activation\"\u003e\u003ccode\u003eActivatable\u003c/code\u003e\u003c/a\u003e, \n\u003ca href\u003d\"https://docs.oracle.com/en/java/javase/16/docs/api/serialized-form.html#java.rmi.activation.ActivationDesc\"\u003eSerialized Form\u003c/a\u003e"
    ],
    "since": [
      "1.2"
    ]
  }
}