{
  "packageName": "org.bukkit.entity",
  "simpleName": "WanderingTrader",
  "moduleName": "ALL-UNNAMED",
  "type": "INTERFACE",
  "superClass": {
    "name": "org.bukkit.entity.AbstractVillager",
    "type": "Class"
  },
  "members": [
    {
      "returnType": {
        "name": "int",
        "type": "Class"
      },
      "parameters": [],
      "isDefaultMethod": false,
      "memberType": "JavaMethod",
      "modifiers": 0,
      "name": "getDespawnDelay",
      "comment": "Gets the despawn delay before this WanderingTrader is forcibly despawned. If this is less than or equal to 0, then the trader will not be despawned.",
      "annotations": [],
      "tagMap": {
        "return": [
          "The despawn delay before this \n\u003ca href\u003d\"https://hub.spigotmc.org/javadocs/bukkit/org/bukkit/entity/WanderingTrader.html\" title\u003d\"interface in org.bukkit.entity\"\u003e\u003ccode\u003eWanderingTrader\u003c/code\u003e\u003c/a\u003e is forcibly despawned"
        ]
      }
    },
    {
      "returnType": {
        "name": "void",
        "type": "Class"
      },
      "parameters": [
        {
          "annotations": [],
          "type": {
            "name": "int",
            "type": "Class"
          },
          "name": "despawnDelay",
          "varargs": false
        }
      ],
      "isDefaultMethod": false,
      "memberType": "JavaMethod",
      "modifiers": 0,
      "name": "setDespawnDelay",
      "comment": "Sets the despawn delay before this WanderingTrader is forcibly despawned. If this is less than or equal to 0, then the trader will not be despawned.",
      "annotations": [],
      "tagMap": {
        "param": [
          "\u003ccode\u003edespawnDelay\u003c/code\u003e - The new despawn delay before this \n\u003ca href\u003d\"https://hub.spigotmc.org/javadocs/bukkit/org/bukkit/entity/WanderingTrader.html\" title\u003d\"interface in org.bukkit.entity\"\u003e\u003ccode\u003eWanderingTrader\u003c/code\u003e\u003c/a\u003e is forcibly despawned"
        ]
      }
    }
  ],
  "memberType": "JavaClass",
  "modifiers": 513,
  "name": "org.bukkit.entity.WanderingTrader",
  "annotations": [],
  "tagMap": {}
}