{
  "packageName": "org.bukkit.block.data.type",
  "simpleName": "Snow",
  "moduleName": "ALL-UNNAMED",
  "type": "INTERFACE",
  "superClass": {
    "name": "org.bukkit.block.data.BlockData",
    "type": "Class"
  },
  "members": [
    {
      "returnType": {
        "name": "int",
        "type": "Class"
      },
      "parameters": [],
      "isDefaultMethod": false,
      "memberType": "JavaMethod",
      "modifiers": 0,
      "name": "getLayers",
      "comment": "Gets the value of the \u0027layers\u0027 property.",
      "annotations": [],
      "tagMap": {
        "return": [
          "the \u0027layers\u0027 value"
        ]
      }
    },
    {
      "returnType": {
        "name": "void",
        "type": "Class"
      },
      "parameters": [
        {
          "annotations": [],
          "type": {
            "name": "int",
            "type": "Class"
          },
          "name": "layers",
          "varargs": false
        }
      ],
      "isDefaultMethod": false,
      "memberType": "JavaMethod",
      "modifiers": 0,
      "name": "setLayers",
      "comment": "Sets the value of the \u0027layers\u0027 property.",
      "annotations": [],
      "tagMap": {
        "param": [
          "\u003ccode\u003elayers\u003c/code\u003e - the new \u0027layers\u0027 value"
        ]
      }
    },
    {
      "returnType": {
        "name": "int",
        "type": "Class"
      },
      "parameters": [],
      "isDefaultMethod": false,
      "memberType": "JavaMethod",
      "modifiers": 0,
      "name": "getMinimumLayers",
      "comment": "Gets the minimum allowed value of the \u0027layers\u0027 property.",
      "annotations": [],
      "tagMap": {
        "return": [
          "the minimum \u0027layers\u0027 value"
        ]
      }
    },
    {
      "returnType": {
        "name": "int",
        "type": "Class"
      },
      "parameters": [],
      "isDefaultMethod": false,
      "memberType": "JavaMethod",
      "modifiers": 0,
      "name": "getMaximumLayers",
      "comment": "Gets the maximum allowed value of the \u0027layers\u0027 property.",
      "annotations": [],
      "tagMap": {
        "return": [
          "the maximum \u0027layers\u0027 value"
        ]
      }
    }
  ],
  "memberType": "JavaClass",
  "modifiers": 513,
  "name": "org.bukkit.block.data.type.Snow",
  "comment": "\u0027layers\u0027 represents the amount of layers of snow which are present in this block. \n\u003cbr\u003e May not be lower than \n\u003ca href\u003d\"#getMinimumLayers()\"\u003e\u003ccode\u003egetMinimumLayers()\u003c/code\u003e\u003c/a\u003e or higher than \n\u003ca href\u003d\"#getMaximumLayers()\"\u003e\u003ccode\u003egetMaximumLayers()\u003c/code\u003e\u003c/a\u003e.",
  "tagMap": {}
}