{
  "packageName": "javax.crypto.spec",
  "simpleName": "DHParameterSpec",
  "moduleName": "java.base",
  "type": "CLASS",
  "superClass": {
    "name": "java.lang.Object",
    "type": "Class"
  },
  "members": [
    {
      "returnType": {
        "name": "java.math.BigInteger",
        "type": "Class"
      },
      "parameters": [],
      "memberType": "JavaMethod",
      "modifiers": 1,
      "name": "getP",
      "comment": "Returns the prime modulus p.",
      "tagMap": {
        "return": [
          "the prime modulus \n\u003ccode\u003ep\u003c/code\u003e"
        ]
      }
    },
    {
      "returnType": {
        "name": "java.math.BigInteger",
        "type": "Class"
      },
      "parameters": [],
      "memberType": "JavaMethod",
      "modifiers": 1,
      "name": "getG",
      "comment": "Returns the base generator g.",
      "tagMap": {
        "return": [
          "the base generator \n\u003ccode\u003eg\u003c/code\u003e"
        ]
      }
    },
    {
      "returnType": {
        "name": "int",
        "type": "Class"
      },
      "parameters": [],
      "memberType": "JavaMethod",
      "modifiers": 1,
      "name": "getL",
      "comment": "Returns the size in bits, l, of the random exponent (private value).",
      "tagMap": {
        "return": [
          "the size in bits, \n\u003ccode\u003el\u003c/code\u003e, of the random exponent (private value), or 0 if this size has not been set"
        ]
      }
    },
    {
      "parameters": [
        {
          "type": {
            "name": "java.math.BigInteger",
            "type": "Class"
          },
          "field": {
            "name": "p"
          }
        },
        {
          "type": {
            "name": "java.math.BigInteger",
            "type": "Class"
          },
          "field": {
            "name": "g"
          }
        }
      ],
      "memberType": "JavaMethod",
      "modifiers": 1,
      "comment": "Constructs a parameter set for Diffie-Hellman, using a prime modulus p and a base generator g.",
      "tagMap": {
        "param": [
          "\u003ccode\u003ep\u003c/code\u003e - the prime modulus",
          "\u003ccode\u003eg\u003c/code\u003e - the base generator"
        ]
      }
    },
    {
      "parameters": [
        {
          "type": {
            "name": "java.math.BigInteger",
            "type": "Class"
          },
          "field": {
            "name": "p"
          }
        },
        {
          "type": {
            "name": "java.math.BigInteger",
            "type": "Class"
          },
          "field": {
            "name": "g"
          }
        },
        {
          "type": {
            "name": "int",
            "type": "Class"
          },
          "field": {
            "name": "l"
          }
        }
      ],
      "memberType": "JavaMethod",
      "modifiers": 1,
      "comment": "Constructs a parameter set for Diffie-Hellman, using a prime modulus p, a base generator g, and the size in bits, l, of the random exponent (private value).",
      "tagMap": {
        "param": [
          "\u003ccode\u003ep\u003c/code\u003e - the prime modulus",
          "\u003ccode\u003eg\u003c/code\u003e - the base generator",
          "\u003ccode\u003el\u003c/code\u003e - the size in bits of the random exponent (private value)"
        ]
      }
    }
  ],
  "memberType": "JavaClass",
  "modifiers": 1,
  "name": "javax.crypto.spec.DHParameterSpec",
  "comment": "This class specifies the set of parameters used with the Diffie-Hellman algorithm, as specified in PKCS #3: \n\u003ci\u003eDiffie-Hellman Key-Agreement Standard\u003c/i\u003e. \n\u003cp\u003eA central authority generates parameters and gives them to the two entities seeking to generate a secret key. The parameters are a prime \u003ccode\u003ep\u003c/code\u003e, a base \u003ccode\u003eg\u003c/code\u003e, and optionally the length in bits of the private value, \u003ccode\u003el\u003c/code\u003e. \u003c/p\u003e\n\u003cp\u003eIt is possible that more than one instance of parameters may be generated by a given central authority, and that there may be more than one central authority. Indeed, each individual may be its own central authority, with different entities having different parameters. \u003c/p\u003e\n\u003cp\u003eNote that this class does not perform any validation on specified parameters. Thus, the specified values are returned directly even if they are null.\u003c/p\u003e",
  "tagMap": {
    "see": [
      "\u003ca href\u003d\"https://docs.oracle.com/en/java/javase/16/docs/api/java.base/javax/crypto/KeyAgreement.html\" title\u003d\"class in javax.crypto\"\u003e\u003ccode\u003eKeyAgreement\u003c/code\u003e\u003c/a\u003e"
    ],
    "since": [
      "1.4"
    ]
  }
}