{
  "packageName": "javax.management",
  "simpleName": "MBeanParameterInfo",
  "moduleName": "java.management",
  "type": "CLASS",
  "superClass": {
    "name": "javax.management.MBeanFeatureInfo",
    "type": "Class"
  },
  "members": [
    {
      "returnType": {
        "name": "java.lang.Object",
        "type": "Class"
      },
      "parameters": [],
      "memberType": "JavaMethod",
      "modifiers": 1,
      "name": "clone",
      "comment": "Returns a shallow clone of this instance. The clone is obtained by simply calling super.clone(), thus calling the default native shallow cloning mechanism implemented by Object.clone(). No deeper cloning of any internal field is made. Since this class is immutable, cloning is chiefly of interest to subclasses.",
      "tagMap": {
        "see": [
          "\u003ca href\u003d\"https://docs.oracle.com/en/java/javase/16/docs/api/java.base/java/lang/Cloneable.html\" title\u003d\"interface in java.lang\"\u003e\u003ccode\u003eCloneable\u003c/code\u003e\u003c/a\u003e"
        ],
        "Overrides:": [
          "\u003ccode\u003e\u003ca href\u003d\"https://docs.oracle.com/en/java/javase/16/docs/api/java.base/java/lang/Object.html#clone()\"\u003eclone\u003c/a\u003e\u003c/code\u003e\u0026nbsp;in class\u0026nbsp;\n\u003ccode\u003e\u003ca href\u003d\"https://docs.oracle.com/en/java/javase/16/docs/api/java.base/java/lang/Object.html\" title\u003d\"class in java.lang\"\u003eObject\u003c/a\u003e\u003c/code\u003e"
        ],
        "return": [
          "a clone of this instance."
        ]
      }
    },
    {
      "returnType": {
        "name": "java.lang.String",
        "type": "Class"
      },
      "parameters": [],
      "memberType": "JavaMethod",
      "modifiers": 1,
      "name": "getType",
      "comment": "Returns the type or class name of the data.",
      "tagMap": {
        "return": [
          "the type string."
        ]
      }
    },
    {
      "returnType": {
        "name": "boolean",
        "type": "Class"
      },
      "parameters": [
        {
          "type": {
            "name": "java.lang.Object",
            "type": "Class"
          },
          "field": {
            "name": "o"
          }
        }
      ],
      "memberType": "JavaMethod",
      "modifiers": 1,
      "name": "equals",
      "comment": "Compare this MBeanParameterInfo to another.",
      "tagMap": {
        "see": [
          "\u003ca href\u003d\"https://docs.oracle.com/en/java/javase/16/docs/api/java.base/java/lang/Object.html#hashCode()\"\u003e\u003ccode\u003eObject.hashCode()\u003c/code\u003e\u003c/a\u003e, \n\u003ca href\u003d\"https://docs.oracle.com/en/java/javase/16/docs/api/java.base/java/util/HashMap.html\" title\u003d\"class in java.util\"\u003e\u003ccode\u003eHashMap\u003c/code\u003e\u003c/a\u003e"
        ],
        "Overrides:": [
          "\u003ccode\u003e\u003ca href\u003d\"https://docs.oracle.com/en/java/javase/16/docs/api/java.management/javax/management/MBeanFeatureInfo.html#equals(java.lang.Object)\"\u003eequals\u003c/a\u003e\u003c/code\u003e\u0026nbsp;in class\u0026nbsp;\n\u003ccode\u003e\u003ca href\u003d\"https://docs.oracle.com/en/java/javase/16/docs/api/java.management/javax/management/MBeanFeatureInfo.html\" title\u003d\"class in javax.management\"\u003eMBeanFeatureInfo\u003c/a\u003e\u003c/code\u003e"
        ],
        "param": [
          "\u003ccode\u003eo\u003c/code\u003e - the object to compare to."
        ],
        "return": [
          "true if and only if \n\u003ccode\u003eo\u003c/code\u003e is an MBeanParameterInfo such that its \n\u003ca href\u003d\"https://docs.oracle.com/en/java/javase/16/docs/api/java.management/javax/management/MBeanFeatureInfo.html#getName()\"\u003e\u003ccode\u003eMBeanFeatureInfo.getName()\u003c/code\u003e\u003c/a\u003e, \n\u003ca href\u003d\"https://docs.oracle.com/en/java/javase/16/docs/api/java.management/javax/management/MBeanParameterInfo.html#getType()\"\u003e\u003ccode\u003egetType()\u003c/code\u003e\u003c/a\u003e, \n\u003ca href\u003d\"https://docs.oracle.com/en/java/javase/16/docs/api/java.management/javax/management/MBeanFeatureInfo.html#getDescriptor()\"\u003e\u003ccode\u003eMBeanFeatureInfo.getDescriptor()\u003c/code\u003e\u003c/a\u003e, and \n\u003ca href\u003d\"https://docs.oracle.com/en/java/javase/16/docs/api/java.management/javax/management/MBeanFeatureInfo.html#getDescription()\"\u003e\u003ccode\u003eMBeanFeatureInfo.getDescription()\u003c/code\u003e\u003c/a\u003e values are equal (not necessarily identical) to those of this MBeanParameterInfo."
        ]
      }
    },
    {
      "parameters": [
        {
          "type": {
            "name": "java.lang.String",
            "type": "Class"
          },
          "field": {
            "name": "name"
          }
        },
        {
          "type": {
            "name": "java.lang.String",
            "type": "Class"
          },
          "field": {
            "name": "type"
          }
        },
        {
          "type": {
            "name": "java.lang.String",
            "type": "Class"
          },
          "field": {
            "name": "description"
          }
        }
      ],
      "memberType": "JavaMethod",
      "modifiers": 1,
      "comment": "Constructs an MBeanParameterInfo object.",
      "tagMap": {
        "param": [
          "\u003ccode\u003ename\u003c/code\u003e - The name of the data",
          "\u003ccode\u003etype\u003c/code\u003e - The type or class name of the data",
          "\u003ccode\u003edescription\u003c/code\u003e - A human readable description of the data. Optional."
        ]
      }
    },
    {
      "parameters": [
        {
          "type": {
            "name": "java.lang.String",
            "type": "Class"
          },
          "field": {
            "name": "name"
          }
        },
        {
          "type": {
            "name": "java.lang.String",
            "type": "Class"
          },
          "field": {
            "name": "type"
          }
        },
        {
          "type": {
            "name": "java.lang.String",
            "type": "Class"
          },
          "field": {
            "name": "description"
          }
        },
        {
          "type": {
            "name": "javax.management.Descriptor",
            "type": "Class"
          },
          "field": {
            "name": "descriptor"
          }
        }
      ],
      "memberType": "JavaMethod",
      "modifiers": 1,
      "comment": "Constructs an MBeanParameterInfo object.",
      "tagMap": {
        "param": [
          "\u003ccode\u003ename\u003c/code\u003e - The name of the data",
          "\u003ccode\u003etype\u003c/code\u003e - The type or class name of the data",
          "\u003ccode\u003edescription\u003c/code\u003e - A human readable description of the data. Optional.",
          "\u003ccode\u003edescriptor\u003c/code\u003e - The descriptor for the operation. This may be null which is equivalent to an empty descriptor."
        ],
        "since": [
          "1.6"
        ]
      }
    }
  ],
  "memberType": "JavaClass",
  "modifiers": 1,
  "name": "javax.management.MBeanParameterInfo",
  "comment": "Describes an argument of an operation exposed by an MBean. Instances of this class are immutable. Subclasses may be mutable but this is not recommended.",
  "tagMap": {
    "see": [
      "\u003ca href\u003d\"https://docs.oracle.com/en/java/javase/16/docs/api/serialized-form.html#javax.management.MBeanParameterInfo\"\u003eSerialized Form\u003c/a\u003e"
    ],
    "since": [
      "1.5"
    ]
  }
}